gt_extras/__init__.py
gt_extras/_utils_color.py
gt_extras/_utils_column.py
gt_extras/colors.py
gt_extras/formatting.py
gt_extras/html.py
gt_extras/icons.py
gt_extras/images.py
gt_extras/plotting.py
gt_extras/styling.py
gt_extras/summary.py
gt_extras/themes.py
gt_extras/tests/conftest.py
gt_extras/tests/test_colors.py
gt_extras/tests/test_formatting.py
gt_extras/tests/test_html.py
gt_extras/tests/test_icons.py
gt_extras/tests/test_images.py
gt_extras/tests/test_plotting.py
gt_extras/tests/test_styling.py
gt_extras/tests/test_summary.py
gt_extras/tests/test_themes.py
gt_extras/tests/test_utils_column.py
gt_extras/tests/__snapshots__/test_colors.ambr
gt_extras/tests/__snapshots__/test_formatting.ambr
gt_extras/tests/__snapshots__/test_html.ambr
gt_extras/tests/__snapshots__/test_icons.ambr
gt_extras/tests/__snapshots__/test_images.ambr
gt_extras/tests/__snapshots__/test_plotting.ambr
gt_extras/tests/__snapshots__/test_summary.ambr
gt_extras/tests/__snapshots__/test_themes.ambr
gt_extras-0.0.8.dist-info/licenses/LICENSE
gt_extras-0.0.8.dist-info/METADATA
gt_extras-0.0.8.dist-info/WHEEL
gt_extras-0.0.8.dist-info/top_level.txt
gt_extras-0.0.8.dist-info/RECORD
