Metadata-Version: 2.4
Name: gt-extras
Version: 0.0.8
Summary: Provides additional functions for creating beautiful tables with 'great-tables'.
Author-email: Jules Walzer-Goldfeld <jules.walzergoldfeld@gmail.com>, Michael Chow <mc_al_github@fastmail.com>, Rich Iannone <rich@posit.co>
License: MIT License
Keywords: tables,html
Classifier: Programming Language :: Python :: 3.9
Classifier: Programming Language :: Python :: 3.10
Classifier: Programming Language :: Python :: 3.11
Classifier: Programming Language :: Python :: 3.12
Requires-Python: >=3.9
License-File: LICENSE
Requires-Dist: faicons>=0.2.2
Requires-Dist: great-tables>=0.18.0
Requires-Dist: scipy>=1.13.1
Requires-Dist: svg-py>=1.6.0
Requires-Dist: narwhals>=1.0.0
Dynamic: license-file
